h3o_polars_ext-0.1.0.dist-info/METADATA
h3o_polars_ext-0.1.0.dist-info/WHEEL
h3o_polars_ext-0.1.0.dist-info/license_files/LICENSE
h3o_polars_ext/__init__.py
LICENSE
README.md
h3o_polars_ext/h3o_polars_ext.cpython-311-darwin.so
h3o_polars_ext-0.1.0.dist-info/RECORD
