Metadata-Version: 2.1
Name: h3o_polars_ext
Version: 0.1.0
Classifier: Development Status :: 3 - Alpha
Classifier: Programming Language :: Rust
Classifier: Programming Language :: Python
Classifier: License :: OSI Approved :: MIT License
License-File: LICENSE
Summary: Add h3o polars extenstions
Author: Sean Lane
License: MIT
Requires-Python: >=3.10
Project-URL: homepage, https://github.com/neiybor/h3o_polars_ext
Project-URL: repository, https://github.com/neiybor/h3o_polars_ext
